pyhifiberry/__init__.py
pyhifiberry/audiocontrol2.py
pyhifiberry/audiocontrol2sio.py
pyhifiberry/consts.py
pyhifiberry/engineio_v4/__init__.py
pyhifiberry/engineio_v4/async_drivers/__init__.py
pyhifiberry/engineio_v4/async_drivers/aiohttp.py
pyhifiberry/engineio_v4/async_drivers/asgi.py
pyhifiberry/engineio_v4/async_drivers/eventlet.py
pyhifiberry/engineio_v4/async_drivers/gevent.py
pyhifiberry/engineio_v4/async_drivers/gevent_uwsgi.py
pyhifiberry/engineio_v4/async_drivers/sanic.py
pyhifiberry/engineio_v4/async_drivers/threading.py
pyhifiberry/engineio_v4/async_drivers/tornado.py
pyhifiberry/engineio_v4/asyncio_client.py
pyhifiberry/engineio_v4/asyncio_server.py
pyhifiberry/engineio_v4/asyncio_socket.py
pyhifiberry/engineio_v4/client.py
pyhifiberry/engineio_v4/exceptions.py
pyhifiberry/engineio_v4/json.py
pyhifiberry/engineio_v4/middleware.py
pyhifiberry/engineio_v4/packet.py
pyhifiberry/engineio_v4/payload.py
pyhifiberry/engineio_v4/server.py
pyhifiberry/engineio_v4/socket.py
pyhifiberry/engineio_v4/static_files.py
pyhifiberry/socketio_v5/__init__.py
pyhifiberry/socketio_v5/asgi.py
pyhifiberry/socketio_v5/asyncio_aiopika_manager.py
pyhifiberry/socketio_v5/asyncio_client.py
pyhifiberry/socketio_v5/asyncio_manager.py
pyhifiberry/socketio_v5/asyncio_namespace.py
pyhifiberry/socketio_v5/asyncio_pubsub_manager.py
pyhifiberry/socketio_v5/asyncio_redis_manager.py
pyhifiberry/socketio_v5/asyncio_server.py
pyhifiberry/socketio_v5/base_manager.py
pyhifiberry/socketio_v5/client.py
pyhifiberry/socketio_v5/exceptions.py
pyhifiberry/socketio_v5/kafka_manager.py
pyhifiberry/socketio_v5/kombu_manager.py
pyhifiberry/socketio_v5/middleware.py
pyhifiberry/socketio_v5/msgpack_packet.py
pyhifiberry/socketio_v5/namespace.py
pyhifiberry/socketio_v5/packet.py
pyhifiberry/socketio_v5/pubsub_manager.py
pyhifiberry/socketio_v5/redis_manager.py
pyhifiberry/socketio_v5/server.py
pyhifiberry/socketio_v5/tornado.py
pyhifiberry/socketio_v5/zmq_manager.py
pyhifiberry-0.1.1.dist-info/LICENSE
pyhifiberry-0.1.1.dist-info/WHEEL
pyhifiberry-0.1.1.dist-info/METADATA
pyhifiberry-0.1.1.dist-info/RECORD
