Metadata-Version: 2.1
Name: pyhifiberry
Version: 0.1.1
Summary: Python library to interface with Hifiberry OS API.
Home-page: https://github.com/schnabel/pyhifiberry
License: MIT
Author: Diogo Gomes
Author-email: diogogomes@gmail.com
Requires-Python: >=3.7,<4.0
Classifier: Intended Audience :: Developers
Classifier: License :: OSI Approved :: MIT License
Classifier: Operating System :: OS Independent
Classifier: Programming Language :: Python
Classifier: Programming Language :: Python :: 3
Classifier: Programming Language :: Python :: 3.10
Classifier: Programming Language :: Python :: 3.7
Classifier: Programming Language :: Python :: 3.8
Classifier: Programming Language :: Python :: 3.9
Classifier: Topic :: Software Development :: Libraries :: Python Modules
Requires-Dist: aiohttp (>=3.8.1,<4.0.0)
Requires-Dist: bidict (>=0.22.0,<0.23.0)
Project-URL: Repository, https://github.com/schnabel/pyhifiberry
